Workbook

Sheet Dashboard
B2: Patrimônio
B3: XP + Itaú/ION + Onze · jun/26 · cotações CPLE3/ITSA4/RANI3/BRST3 ao vivo · manuais atualize 1x/mês
B6: PATRIMÔNIO TOTAL | F6: TOTAL APLICADO
B7: =Carteira!I24 -> 163348.38 | F7: =Carteira!F24 -> 104577.69
B9: RENDIMENTO (R$) | F9: RENDIMENTO (%)
B10: =Carteira!J24 -> 58770.69 | F10: =Carteira!K24 -> 0.56198115
B13: Por instituição
C14: Valor | D14: %
B15: XP | C15: =SUMIF(Carteira!$A$5:$A$23,$B15,Carteira!$I$5:$I$23) -> 24896.17 | D15: =IFERROR(C15/$C$18,"") -> 0.15241149
B16: Itaú/ION | C16: =SUMIF(Carteira!$A$5:$A$23,$B16,Carteira!$I$5:$I$23) -> 55890.66 | D16: =IFERROR(C16/$C$18,"") -> 0.34215619
B17: Onze | C17: =SUMIF(Carteira!$A$5:$A$23,$B17,Carteira!$I$5:$I$23) -> 82561.55 | D17: =IFERROR(C17/$C$18,"") -> 0.50543232
B18: Total | C18: =Carteira!I24 -> 163348.38
B20: Por classe
C21: Valor | D21: %
B22: Ação/FII | C22: =SUMIF(Carteira!$B$5:$B$23,$B22,Carteira!$I$5:$I$23) -> 1706.45 | D22: =IFERROR(C22/$C$27,"") -> 0.010446691
B23: Fundo | C23: =SUMIF(Carteira!$B$5:$B$23,$B23,Carteira!$I$5:$I$23) -> 13982.08 | D23: =IFERROR(C23/$C$27,"") -> 0.085596686
B24: Previdência | C24: =SUMIF(Carteira!$B$5:$B$23,$B24,Carteira!$I$5:$I$23) -> 125490.17 | D24: =IFERROR(C24/$C$27,"") -> 0.76823639
B25: Cofrinhos | C25: =SUMIF(Carteira!$B$5:$B$23,$B25,Carteira!$I$5:$I$23) -> 21867.67 | D25: =IFERROR(C25/$C$27,"") -> 0.13387136
B26: Poupança | C26: =SUMIF(Carteira!$B$5:$B$23,$B26,Carteira!$I$5:$I$23) -> 302.01 | D26: =IFERROR(C26/$C$27,"") -> 0.0018488705
B27: Total | C27: =Carteira!I24 -> 163348.38

Sheet Carteira
A1: Carteira · XP + Itaú/ION + Onze (jun/26)
A2: Cotação automática: CPLE3, ITSA4, RANI3, BRST3. Demais: atualize 'Saldo Manual' 1x/mês. Âmbar = resgate pendente XP.
A4: Instituição | B4: Classe | C4: Ativo | D4: Ticker | E4: Qtd | F4: Valor Aplicado | G4: Cotação Atual | H4: Saldo Manual | I4: Saldo Atual | J4: Rendimento R$ | K4: Rend. % | L4: Obs.
A5: XP | B5: Ação/FII | C5: CPLE3 · Copel | D5: CPLE3 | E5: 28 | F5: 373.52 | G5: =IFERROR(googlefinance("BVMF:"&D5),"") | I5: =IF(D5<>"",IF(ISNUMBER(G5),E5*G5,F5),IF(H5<>"",H5,IF(F5<>"",F5,""))) -> 373.52 | J5: =IF(OR(F5="",I5=""),"",I5-F5) -> 0 | K5: =IFERROR((I5-F5)/F5,"") -> 0
A6: XP | B6: Ação/FII | C6: ITSA4 · Itausa | D6: ITSA4 | E6: 27 | F6: 373.68 | G6: =IFERROR(googlefinance("BVMF:"&D6),"") | I6: =IF(D6<>"",IF(ISNUMBER(G6),E6*G6,F6),IF(H6<>"",H6,IF(F6<>"",F6,""))) -> 373.68 | J6: =IF(OR(F6="",I6=""),"",I6-F6) -> 0 | K6: =IFERROR((I6-F6)/F6,"") -> 0
A7: XP | B7: Ação/FII | C7: RANI3 · Irani | D7: RANI3 | E7: 41 | F7: 373.1 | G7: =IFERROR(googlefinance("BVMF:"&D7),"") | I7: =IF(D7<>"",IF(ISNUMBER(G7),E7*G7,F7),IF(H7<>"",H7,IF(F7<>"",F7,""))) -> 373.1 | J7: =IF(OR(F7="",I7=""),"",I7-F7) -> 0 | K7: =IFERROR((I7-F7)/F7,"") -> 0
A8: XP | B8: Previdência | C8: AZ Quest Luce Icatu Prev PGBL | F8: 10000 | G8: =IFERROR(googlefinance("BVMF:"&D8),"") | H8: 12362.16 | I8: =IF(D8<>"",IF(ISNUMBER(G8),E8*G8,F8),IF(H8<>"",H8,IF(F8<>"",F8,""))) -> 12362.16 | J8: =IF(OR(F8="",I8=""),"",I8-F8) -> 2362.16 | K8: =IFERROR((I8-F8)/F8,"") -> 0.236216
A9: XP | B9: Fundo | C9: Western Asset US Index 500 FIF | F9: 4150.21 | G9: =IFERROR(googlefinance("BVMF:"&D9),"") | H9: 4562.77 | I9: =IF(D9<>"",IF(ISNUMBER(G9),E9*G9,F9),IF(H9<>"",H9,IF(F9<>"",F9,""))) -> 4562.77 | J9: =IF(OR(F9="",I9=""),"",I9-F9) -> 412.56 | K9: =IFERROR((I9-F9)/F9,"") -> 0.099407018
A10: XP | B10: Fundo | C10: ACE Capital Multicenários FC FIF | F10: 1447.64 | G10: =IFERROR(googlefinance("BVMF:"&D10),"") | H10: 1478.02 | I10: =IF(D10<>"",IF(ISNUMBER(G10),E10*G10,F10),IF(H10<>"",H10,IF(F10<>"",F10,""))) -> 1478.02 | J10: =IF(OR(F10="",I10=""),"",I10-F10) -> 30.38 | K10: =IFERROR((I10-F10)/F10,"") -> 0.02098588
A11: XP | B11: Fundo | C11: Trend Ouro FIF Multi RL | F11: 952.87 | G11: =IFERROR(googlefinance("BVMF:"&D11),"") | H11: 1261.6 | I11: =IF(D11<>"",IF(ISNUMBER(G11),E11*G11,F11),IF(H11<>"",H11,IF(F11<>"",F11,""))) -> 1261.6 | J11: =IF(OR(F11="",I11=""),"",I11-F11) -> 308.73 | K11: =IFERROR((I11-F11)/F11,"") -> 0.32400013 | L11: parte em resgate
A12: XP | B12: Fundo | C12: Selection RF Light FIC FIRF CP LP | F12: 984.64 | G12: =IFERROR(googlefinance("BVMF:"&D12),"") | H12: 1099.5 | I12: =IF(D12<>"",IF(ISNUMBER(G12),E12*G12,F12),IF(H12<>"",H12,IF(F12<>"",F12,""))) -> 1099.5 | J12: =IF(OR(F12="",I12=""),"",I12-F12) -> 114.86 | K12: =IFERROR((I12-F12)/F12,"") -> 0.11665177 | L12: liq. 24/jun
A13: XP | B13: Fundo | C13: Legacy Capital Compound Advisory FIF | F13: 1900 | G13: =IFERROR(googlefinance("BVMF:"&D13),"") | H13: 1999.63 | I13: =IF(D13<>"",IF(ISNUMBER(G13),E13*G13,F13),IF(H13<>"",H13,IF(F13<>"",F13,""))) -> 1999.63 | J13: =IF(OR(F13="",I13=""),"",I13-F13) -> 99.63 | K13: =IFERROR((I13-F13)/F13,"") -> 0.052436842 | L13: liq. 14/jul
A14: XP | B14: Fundo | C14: Trend Valor Brasil FIA RL | F14: 750 | G14: =IFERROR(googlefinance("BVMF:"&D14),"") | H14: 877.1 | I14: =IF(D14<>"",IF(ISNUMBER(G14),E14*G14,F14),IF(H14<>"",H14,IF(F14<>"",F14,""))) -> 877.1 | J14: =IF(OR(F14="",I14=""),"",I14-F14) -> 127.1 | K14: =IFERROR((I14-F14)/F14,"") -> 0.16946667 | L14: entrada casa nova
A15: XP | B15: Fundo | C15: Trend Fixed Income US Target Duration | F15: 124.33 | G15: =IFERROR(googlefinance("BVMF:"&D15),"") | H15: 135.09 | I15: =IF(D15<>"",IF(ISNUMBER(G15),E15*G15,F15),IF(H15<>"",H15,IF(F15<>"",F15,""))) -> 135.09 | J15: =IF(OR(F15="",I15=""),"",I15-F15) -> 10.76 | K15: =IFERROR((I15-F15)/F15,"") -> 0.086543875 | L15: resgate total
A16: Itaú/ION | B16: Ação/FII | C16: BRST3 · BrasilAgro | D16: BRST3 | E16: 200 | F16: 586.15 | G16: =IFERROR(googlefinance("BVMF:"&D16),"") | I16: =IF(D16<>"",IF(ISNUMBER(G16),E16*G16,F16),IF(H16<>"",H16,IF(F16<>"",F16,""))) -> 586.15 | J16: =IF(OR(F16="",I16=""),"",I16-F16) -> 0 | K16: =IFERROR((I16-F16)/F16,"") -> 0
A17: Itaú/ION | B17: Previdência | C17: Itaú Kinea Andes Prev RF CP PGBL | G17: =IFERROR(googlefinance("BVMF:"&D17),"") | H17: 30566.46 | I17: =IF(D17<>"",IF(ISNUMBER(G17),E17*G17,F17),IF(H17<>"",H17,IF(F17<>"",F17,""))) -> 30566.46 | J17: =IF(OR(F17="",I17=""),"",I17-F17) | K17: =IFERROR((I17-F17)/F17,"")
A18: Itaú/ION | B18: Cofrinhos | C18: Cofrinhos ION | G18: =IFERROR(googlefinance("BVMF:"&D18),"") | H18: 21867.67 | I18: =IF(D18<>"",IF(ISNUMBER(G18),E18*G18,F18),IF(H18<>"",H18,IF(F18<>"",F18,""))) -> 21867.67 | J18: =IF(OR(F18="",I18=""),"",I18-F18) | K18: =IFERROR((I18-F18)/F18,"") | L18: rend 2026: R$335
A19: Itaú/ION | B19: Fundo | C19: Itaú Kinea Andes RF CP LP | G19: =IFERROR(googlefinance("BVMF:"&D19),"") | H19: 2568.37 | I19: =IF(D19<>"",IF(ISNUMBER(G19),E19*G19,F19),IF(H19<>"",H19,IF(F19<>"",F19,""))) -> 2568.37 | J19: =IF(OR(F19="",I19=""),"",I19-F19) | K19: =IFERROR((I19-F19)/F19,"") | L19: saldo bruto
A20: Itaú/ION | B20: Poupança | C20: Poupança MULTIDATA | G20: =IFERROR(googlefinance("BVMF:"&D20),"") | H20: 302.01 | I20: =IF(D20<>"",IF(ISNUMBER(G20),E20*G20,F20),IF(H20<>"",H20,IF(F20<>"",F20,""))) -> 302.01 | J20: =IF(OR(F20="",I20=""),"",I20-F20) | K20: =IFERROR((I20-F20)/F20,"")
A21: Onze | B21: Previdência | C21: Schroder Icatu Prev Low Vol Multimercado | F21: 23968.24 | G21: =IFERROR(googlefinance("BVMF:"&D21),"") | H21: 23968.24 | I21: =IF(D21<>"",IF(ISNUMBER(G21),E21*G21,F21),IF(H21<>"",H21,IF(F21<>"",F21,""))) -> 23968.24 | J21: =IF(OR(F21="",I21=""),"",I21-F21) -> 0 | K21: =IFERROR((I21-F21)/F21,"") -> 0 | L21: confirme saldo no app
A22: Onze | B22: Previdência | C22: Icatu Seg FIC Empresarial Renda Fixa | F22: 8432.36 | G22: =IFERROR(googlefinance("BVMF:"&D22),"") | H22: 8432.36 | I22: =IF(D22<>"",IF(ISNUMBER(G22),E22*G22,F22),IF(H22<>"",H22,IF(F22<>"",F22,""))) -> 8432.36 | J22: =IF(OR(F22="",I22=""),"",I22-F22) -> 0 | K22: =IFERROR((I22-F22)/F22,"") -> 0 | L22: confirme saldo no app
A23: Onze | B23: Previdência | C23: Icatu Vanguarda Pós Fixado RF Prev | F23: 50160.95 | G23: =IFERROR(googlefinance("BVMF:"&D23),"") | H23: 50160.95 | I23: =IF(D23<>"",IF(ISNUMBER(G23),E23*G23,F23),IF(H23<>"",H23,IF(F23<>"",F23,""))) -> 50160.95 | J23: =IF(OR(F23="",I23=""),"",I23-F23) -> 0 | K23: =IFERROR((I23-F23)/F23,"") -> 0 | L23: confirme saldo no app
A24: Total geral | F24: =SUMIF(F5:F23,"<>",F5:F23) -> 104577.69 | I24: =SUMIF(I5:I23,"<>",I5:I23) -> 163348.38 | J24: =IFERROR(I24-F24,"") -> 58770.69 | K24: =IFERROR((I24-F24)/F24,"") -> 0.56198115

Sheet Histórico
B1: Histórico mensal
B2: 1x/mês: cole o Patrimônio e o Aplicado do Dashboard. Rendimento é calculado automaticamente.
B4: Mês | C4: Patrimônio Total | D4: Total Aplicado | E4: Rendimento R$
B5: jan/26 | E5: =IF(C5="","",C5-D5)
B6: fev/26 | E6: =IF(C6="","",C6-D6)
B7: mar/26 | E7: =IF(C7="","",C7-D7)
B8: abr/26 | E8: =IF(C8="","",C8-D8)
B9: mai/26 | E9: =IF(C9="","",C9-D9)
B10: jun/26 | E10: =IF(C10="","",C10-D10)
B11: jul/26 | E11: =IF(C11="","",C11-D11)
B12: ago/26 | E12: =IF(C12="","",C12-D12)
B13: set/26 | E13: =IF(C13="","",C13-D13)
B14: out/26 | E14: =IF(C14="","",C14-D14)
B15: nov/26 | E15: =IF(C15="","",C15-D15)
B16: dez/26 | E16: =IF(C16="","",C16-D16)

Sheet Config
A1: Instituições | B1: Classes | E1: Como usar
A2: XP | B2: Ação/FII
A3: Itaú/ION | B3: Fundo | E3: 1) Baixe e importe no Google Sheets: Drive → Novo → Fazer upload → abre o arquivo → Arquivo → Salvar como Planilha Google.
A4: Onze | B4: Renda Fixa
A5: Outros | B5: Tesouro Direto | E5: 2) CARTEIRA é o único lugar onde você digita. Cotações automáticas: CPLE3, ITSA4, RANI3, BRST3.
B6: Previdência
B7: Poupança | E7: 3) Linhas ÂMBAR = fundos XP em resgate (entrada casa nova). Apague depois que liquidarem (24/jun e 14/jul).
B8: Cofrinhos
E9: 4) Onze: 'Valor investido' da tela pode ser o aportado — confirme o saldo atual no app e atualize coluna H.
E11: 5) Itaú Kinea Andes PGBL e Cofrinhos: preencha 'Valor Aplicado' com o valor que você aportou no total.
